docker_tasks/__init__.py
docker_tasks/cli.py
docker_tasks-0.1.1.dist-info/METADATA
docker_tasks-0.1.1.dist-info/WHEEL
docker_tasks-0.1.1.dist-info/entry_points.txt
docker_tasks-0.1.1.dist-info/RECORD
