Metadata-Version: 2.1
Name: docker-tasks
Version: 0.1.1
Summary: Run periodic tasks via docker exec
License: BSD
Author: Reimund Klain
Author-email: reimund.klain@condevtec.de
Requires-Python: >=3.8,<4.0
Classifier: License :: Other/Proprietary License
Classifier: Programming Language :: Python :: 3
Classifier: Programming Language :: Python :: 3.8
Classifier: Programming Language :: Python :: 3.9
Classifier: Programming Language :: Python :: 3.10
Classifier: Programming Language :: Python :: 3.11
Classifier: Programming Language :: Python :: 3.12
Requires-Dist: docker (>=6.1.3,<7.0.0)
Requires-Dist: pyparsing (>=3.1.1,<4.0.0)
Requires-Dist: pyyaml (>=6.0.1,<7.0.0)
